setup.py
face_detect/__init__.py
face_detect/cv_tools.py
face_detect_v0.egg-info/PKG-INFO
face_detect_v0.egg-info/SOURCES.txt
face_detect_v0.egg-info/dependency_links.txt
face_detect_v0.egg-info/not-zip-safe
face_detect_v0.egg-info/top_level.txt