Metadata-Version: 1.0
Name: face-detect-v0
Version: 0.1
Summary: Face detector
Home-page: http://github.com/
Author: Natchanon Thepyasuwan
Author-email: nat.chanon@outlook.com
License: MIT
Platform: UNKNOWN
